{
  "materials": [
    {
      "name": "sh_base01",
      "shader_group": "FxDefault02",
      "render_layer": 0,
      "shader_index": 0,
      "texture_maps": [
        {
          "sampler": "LightTableTex",
          "texture": "fxmt_cmn_lt001_m_lta.png",
          "tex_index": 0
        },
        {
          "sampler": "Tex01WRAP",
          "texture": "fxmt_3_bone201_a.png",
          "tex_index": 1
        },
        {
          "sampler": "HighLightTableTex",
          "texture": "fxmt_cmn_ht004_m_lta.png",
          "tex_index": 2
        }
      ],
      "colors": [
        {
          "name": "OutLineCol",
          "r": 0.2847,
          "g": 0.25,
          "b": 0.1395
        },
        {
          "name": "Shadow_Color",
          "r": 0.7835,
          "g": 0.7617,
          "b": 0.6797
        },
        {
          "name": "HighLight_Color",
          "r": 1.0,
          "g": 1.0,
          "b": 1.0
        },
        {
          "name": "Tex01_Multiply_Color",
          "r": 1.0,
          "g": 1.0,
          "b": 1.0
        }
      ],
      "values": [
        {
          "name": "OutLineID",
          "value": 0.0
        },
        {
          "name": "ProgID",
          "value": 0.0
        },
        {
          "name": "ShadowRange",
          "value": 1.0
        },
        {
          "name": "Tex01TranslateU",
          "value": 0.0
        },
        {
          "name": "Tex01TranslateV",
          "value": 0.0
        },
        {
          "name": "Tex01Rotate",
          "value": 0.0
        },
        {
          "name": "Tex01ScaleU",
          "value": 1.0
        },
        {
          "name": "Tex01ScaleV",
          "value": 1.0
        },
        {
          "name": "R0_A1_Tex01_Alpha",
          "value": 1.0
        },
        {
          "name": "HighLightRange",
          "value": 1.0
        }
      ],
      "switches": [
        {
          "name": "OutLineIDEnable",
          "value": true
        },
        {
          "name": "OutLineColFixed",
          "value": true
        }
      ],
      "textures_used": [
        {
          "sampler": "LightTableTex",
          "texture": "fxmt_cmn_lt001_m_lta.png",
          "envtype": "modulate"
        }
      ],
      "used_texture": "fxmt_cmn_lt001_m_lta.png",
      "used_sampler": "LightTableTex"
    }
  ],
  "meshes": [
    {
      "index": 0,
      "num_vertices": 280,
      "num_faces": 464,
      "material_indices": [
        0
      ]
    }
  ],
  "texture_names": [
    "fxmt_cmn_lt001_m_lta",
    "fxmt_3_bone201_a",
    "fxmt_cmn_ht004_m_lta"
  ],
  "hidden_materials": [],
  "outline_materials": []
}